README.md
setup.py
test/__init__.py
test/test.py
wellapplication/MannKendall.py
wellapplication/__init__.py
wellapplication/arcpy_functions.py
wellapplication/chem.py
wellapplication/graphs.py
wellapplication/hydropy.py
wellapplication/mesopy.py
wellapplication/ros.py
wellapplication/transport.py
wellapplication/usgs.py
wellapplication.egg-info/PKG-INFO
wellapplication.egg-info/SOURCES.txt
wellapplication.egg-info/dependency_links.txt
wellapplication.egg-info/requires.txt
wellapplication.egg-info/top_level.txt