Metadata-Version: 1.0
Name: wellapplication
Version: 0.5.3
Summary: Interface with xle files; analyze hydrographs; plot hydrographs; download USGS data
Home-page: https://github.com/inkenbrandt/WellApplication
Author: Paul Inkenbrandt
Author-email: paulinkenbrandt@utah.gov
License: LICENSE.txt
Platform: UNKNOWN
